LICENSE
hjlab_email/__init__.py
hjlab_email/email_service.py
hjlab_email-1.0.1.dist-info/LICENSE
hjlab_email-1.0.1.dist-info/METADATA
hjlab_email-1.0.1.dist-info/WHEEL
hjlab_email-1.0.1.dist-info/RECORD
